{
    "AX": {
        "error": 0.008193840596023412,
        "error_type": "SEM",
        "filter_outliers_dict": {
            "filter_outliers": true,
            "iterations": 1,
            "std_devs": 2
        },
        "fit": "Average",
        "fn": 19,
        "include_baseline_error": false,
        "n": 20,
        "reviewed": true,
        "value": -0.19332735475740934
    },
    "CDD": {
        "error": 4.783358793334224e-05,
        "error_type": "SEM",
        "filter_outliers_dict": {
            "filter_outliers": true,
            "iterations": 1,
            "std_devs": 10
        },
        "fit": "Average",
        "fn": 20,
        "include_baseline_error": false,
        "n": 20,
        "reviewed": true,
        "value": 0.00042806657729670404
    },
    "H1": {
        "error": 0.012994055516169063,
        "error_type": "SEM",
        "filter_outliers_dict": {
            "filter_outliers": true,
            "iterations": 1,
            "std_devs": 2
        },
        "fit": "Average",
        "fn": 20,
        "include_baseline_error": false,
        "n": 20,
        "reviewed": true,
        "value": 0.0343371280701831
    },
    "H2": {
        "error": 0.006651374154174532,
        "error_type": "SEM",
        "filter_outliers_dict": {
            "filter_outliers": true,
            "iterations": 1,
            "std_devs": 2
        },
        "fit": "average",
        "value": -0.03822116583542364
    },
    "L1": {
        "error": 0.007385234017565231,
        "error_type": "SEM",
        "filter_outliers_dict": {
            "filter_outliers": true,
            "iterations": 1,
            "std_devs": 2
        },
        "fit": "Average",
        "fn": 20,
        "include_baseline_error": false,
        "n": 20,
        "reviewed": true,
        "value": -0.005753871986962622
    },
    "L2": {
        "error": 0.013998031152587598,
        "error_type": "SEM",
        "filter_outliers_dict": {
            "filter_outliers": true,
            "iterations": 1,
            "std_devs": 2
        },
        "fit": "Average",
        "fn": 20,
        "include_baseline_error": false,
        "n": 20,
        "reviewed": true,
        "value": 0.03679709077259759
    }
}